xdoctl/__init__.py
xdoctl/keyboard.py
xdoctl/misc.py
xdoctl/mouse.py
xdoctl/window.py
python_xdoctl-0.1.0.post2.dist-info/LICENSE
python_xdoctl-0.1.0.post2.dist-info/METADATA
python_xdoctl-0.1.0.post2.dist-info/WHEEL
python_xdoctl-0.1.0.post2.dist-info/top_level.txt
python_xdoctl-0.1.0.post2.dist-info/RECORD
