Metadata-Version: 2.1
Name: python-xdoctl
Version: 0.1.0.post2
Summary: Xdotool 命令包装器
Home-page: https://github.com/nukemiko/python-xdoctl
Author: nukemiko
Author-email: north666dakota@gmail.com
License: MIT
Keywords: xdotool,libxdo,xdo,mouse,keyboard
Platform: linux
Requires-Python: >=3.8
License-File: LICENSE
